oss_savings/__init__.py
oss_savings/analyze.py
oss_savings/calculator.py
oss_savings/cli.py
oss_savings/deps.py
oss_savings-0.1.4.dist-info/METADATA
oss_savings-0.1.4.dist-info/WHEEL
oss_savings-0.1.4.dist-info/entry_points.txt
oss_savings-0.1.4.dist-info/top_level.txt
oss_savings-0.1.4.dist-info/RECORD
