Metadata-Version: 2.4
Name: oss-savings
Version: 0.1.4
Summary: Calculate how much money open source saved you
Author-email: Pradeep Elankumaran <pradeepe@gmail.com>
License: MIT
Project-URL: Homepage, https://github.com/skyfallsin/oss-savings
Project-URL: Repository, https://github.com/skyfallsin/oss-savings
Project-URL: Issues, https://github.com/skyfallsin/oss-savings/issues
Keywords: open-source,oss,cost-estimation,dependencies,cocomo
Classifier: Development Status :: 4 - Beta
Classifier: Environment :: Console
Classifier: Intended Audience :: Developers
Classifier: Programming Language :: Python :: 3
Classifier: Programming Language :: Python :: 3.10
Classifier: Programming Language :: Python :: 3.11
Classifier: Programming Language :: Python :: 3.12
Classifier: Programming Language :: Python :: 3.13
Classifier: Topic :: Software Development
Requires-Python: >=3.10
Requires-Dist: rich>=13.0.0
